Metadata-Version: 2.1
Name: xmlbind
Version: 0.0.5
Summary: A xml decorator package.
